nrmk_client/EtherCATCommgRPCServer_pb2.py
nrmk_client/EtherCATCommgRPCServer_pb2_grpc.py
nrmk_client/MobygRPCServer_pb2.py
nrmk_client/MobygRPCServer_pb2_grpc.py
nrmk_client/MotorControlgRPCServer_pb2.py
nrmk_client/MotorControlgRPCServer_pb2_grpc.py
nrmk_client/__init__.py
nrmk_client/ecat_grpc_client.py
nrmk_client/moby_grpc_client.py
nrmk_client/motor_grpc_client.py
nrmk_clients-0.1.0.dist-info/METADATA
nrmk_clients-0.1.0.dist-info/WHEEL
nrmk_clients-0.1.0.dist-info/top_level.txt
nrmk_clients-0.1.0.dist-info/RECORD
