Metadata-Version: 2.1
Name: nrmk-clients
Version: 0.1.0
Summary: A gRPC client for EtherCAT communication tasks
Home-page: https://github.com/yourusername/ecat_grpc_client
Author: Neuromeka
Author-email: youngjin.heo@neuromeka.com
License: UNKNOWN
Platform: UNKNOWN
Classifier: Development Status :: 3 - Alpha
Classifier: Intended Audience :: Developers
Classifier: License :: OSI Approved :: MIT License
Classifier: Operating System :: OS Independent
Classifier: Programming Language :: Python :: 3
Classifier: Programming Language :: Python :: 3.6
Classifier: Programming Language :: Python :: 3.7
Classifier: Programming Language :: Python :: 3.8
Classifier: Programming Language :: Python :: 3.9
Requires-Python: >=3.6
Requires-Dist: grpcio (==1.51.3)
Requires-Dist: grpcio-tools (==1.51.3)
Requires-Dist: protobuf (==3.17.3)
